{
    "sources": [
        {
            "type": "directory",
            "source": "entity/signs",
            "prefix": "entity/signs/"
        },
        {
            "type": "directory",
            "source": "entity/boat",
            "prefix": "entity/boat/"
        },
        {
            "type": "single",
            "resource": "entity/minecart"
        },
        {
            "type": "single",
            "resource": "painting/aztec"
        },
        {
            "type": "single",
            "resource": "painting/back"
        },
        {
            "type": "single",
            "resource": "entity/armorstand/wood"
        },
        {
            "type": "single",
            "resource": "entity/end_crystal/end_crystal"
        },
        {
            "type": "single",
            "resource": "entity/chest/normal"
        }
    ]
}
